pornhub/__init__.py
pornhub/core.py
pornhub/photos.py
pornhub/stars.py
pornhub/videos.py
pornhubapi-0.1.0.dist-info/METADATA
pornhubapi-0.1.0.dist-info/WHEEL
pornhubapi-0.1.0.dist-info/top_level.txt
pornhubapi-0.1.0.dist-info/RECORD
