Metadata-Version: 1.0
Name: pornhubapi
Version: 0.1.0
Summary: Pornhub API Wrapper
Home-page: https://github.com/sskender/pornhub-api
Author: diogenesjunior
Author-email: diogenesjunior@protonmail.com
License: MIT
Keywords: pornhub api
Platform: UNKNOWN
